_cottus_C.cpython-312-x86_64-linux-gnu.so
cottus/__init__.py
cottus/model.py
cottus/csrc/CMakeLists.txt
cottus/csrc/block_allocator.cpp
cottus/csrc/block_allocator.h
cottus/csrc/compute_primitives_cpu.cpp
cottus/csrc/compute_primitives_cpu.h
cottus/csrc/compute_primitives_cuda.cu
cottus/csrc/compute_primitives_cuda.h
cottus/csrc/engine.cpp
cottus/csrc/engine.h
cottus/csrc/generic_transformer.cpp
cottus/csrc/generic_transformer.h
cottus/csrc/page_table.cpp
cottus/csrc/page_table.h
cottus/csrc/paged_attention_cpu.cpp
cottus/csrc/paged_attention_cpu.h
cottus/csrc/paged_attention_cuda.cu
cottus/csrc/paged_attention_cuda.h
cottus/csrc/pybind_wrapper.cpp
cottus-0.1.0.dist-info/METADATA
cottus-0.1.0.dist-info/WHEEL
cottus-0.1.0.dist-info/top_level.txt
cottus-0.1.0.dist-info/RECORD
cottus-0.1.0.dist-info/licenses/LICENSE
