Metadata-Version: 2.4
Name: cottus
Version: 0.1.0
Summary: High-performance Llama inference engine
Author: Cottus Team
License: Apache License 2.0
Classifier: Programming Language :: Python :: 3
Classifier: Programming Language :: C++
Requires-Python: >=3.8
License-File: LICENSE
Requires-Dist: torch>=2.0.0
Requires-Dist: transformers
Requires-Dist: safetensors
Dynamic: license-file
